nakalator.py
lib/Nakalator.py
lib/NakalatorAPIRequest.py
lib/__init__.py
lib/constants.py
lib/templates.py
lib/bridge/__init__.py
lib/bridge/nakala_request.dylib
lib/bridge/nakala_request.so
lib/bridge/nkl_gotils.py
lib/utils/__init__.py
lib/utils/cli_utils.py
lib/utils/io_utils.py
lib/utils/tests_utils.py
nakalator-0.0.2.dist-info/METADATA
nakalator-0.0.2.dist-info/WHEEL
nakalator-0.0.2.dist-info/entry_points.txt
nakalator-0.0.2.dist-info/top_level.txt
nakalator-0.0.2.dist-info/RECORD
